simple_vcs/__init__.py
simple_vcs/cli.py
simple_vcs/core.py
simple_vcs/utils.py
simple_vcs-1.1.0.dist-info/licenses/LICENSE
simple_vcs-1.1.0.dist-info/METADATA
simple_vcs-1.1.0.dist-info/WHEEL
simple_vcs-1.1.0.dist-info/entry_points.txt
simple_vcs-1.1.0.dist-info/top_level.txt
simple_vcs-1.1.0.dist-info/RECORD
