Metadata-Version: 2.4
Name: simple-vcs
Version: 1.1.0
Summary: A simple version control system with unique features for easy version management
Home-page: https://github.com/muhammadsufiyanbaig/simple_vcs
Author: Muhammad Sufiyan Baig
Author-email: Muhammad Sufiyan Baig <send.sufiyan@gmail.com>
License: MIT License
Project-URL: Homepage, https://github.com/muhammadsufiyanbaig/simple_vcs/
Project-URL: Repository, https://github.com/muhammadsufiyanbaig/simple_vcs.git
Project-URL: Issues, https://github.com/muhammadsufiyanbaig/simple_vcs/issues
Keywords: version-control,vcs,simple-vcs,backup,snapshot
Requires-Python: >=3.7
License-File: LICENSE
Requires-Dist: click>=7.0
Dynamic: author
Dynamic: home-page
Dynamic: license-file
Dynamic: requires-python
